{
  "wifi-ssid": "wokwi-GUEST",
  "wifi-ssid2": "",
  "mdns": "wokwi",
  "id": "",
  "ota-url": "",
  "temp-format": "C",
  "http-push": "",
  "http-push-h1": "",
  "http-push-h2": "",
  "http-push2": "",
  "http-push2-h1": "",
  "http-push2-h2": "",
  "token": "",
  "token2": "",
  "http-push3": "",
  "influxdb2-push": "",
  "influxdb2-org": "",
  "influxdb2-bucket": "",
  "influxdb2-auth": "",
  "mqtt-push": "",
  "mqtt-port": 1883,
  "mqtt-user": "",
  "mqtt-pass": "",
  "storage-sleep": false,
  "sleep-interval": 30,
  "voltage-factor": 1.59,
  "voltage-config": 4.15,
  "gravity-formula": "0.0*tilt^3+0.0*tilt^2+0.0017978*tilt+0.9436",
  "gravity-format": "G",
  "temp-adjustment-value": 0,
  "gravity-temp-adjustment": false,
  "gyro-temp": false,
  "gyro-calibration-data": {
      "ax": -330,
      "ay": -2249,
      "az": 1170,
      "gx": 99,
      "gy": -6,
      "gz": 4
  },
  "formula-calculation-data": {
      "a1": 25,
      "a3": 35,
      "a2": 45,
      "a4": 55,
      "a5": 30,
      "a6": 30,
      "a7": 30,
      "a8": 30,
      "a9": 30,
      "a10": 30,
      "g1": 1.000,
      "g3": 1.010,
      "g2": 1.025,
      "g4": 1.040,
      "g5": 1.005,
      "g6": 1.005,
      "g7": 1.005,
      "g8": 1.005,
      "g9": 1.005,
      "g10": 1.005
  },
  "ble": ""
}